alphamap/__init__.py
alphamap/_nbdev.py
alphamap/gui.py
alphamap/importing.py
alphamap/organisms_data.py
alphamap/pdflib.py
alphamap/preprocessing.py
alphamap/proteolytic_cleavage.py
alphamap/sequenceplot.py
alphamap/uniprot_integration.py
alphamap/data/alphamap_tutorial.docx
alphamap/data/alphamap_tutorial.pdf
alphamap/data/gui_style.css
alphamap/data/spectronaut_export_scheme.rs
alphamap/data/test_maxquant_input.txt
alphamap/data/img/AlphaMap_example_plot.png
alphamap/data/img/alphamap_icon.png
alphamap/data/img/github.png
alphamap/data/img/max-planck-gesellschaft.jpg
alphamap/data/img/mpi_logo.png
alphamap/data/img/pdb_logo.png
alphamap/data/img/peptide_atlas_logo.png
alphamap/data/img/phosphosite_logo.png
alphamap/data/img/protter_logo.png
alphamap/data/img/uniprot_logo.png
alphamap/js/alphafold-viz.css
alphamap/js/alphafold-viz.js
alphamap/js/uglyfy.sh
release/pyinstaller/alphamap_pyinstaller.py
requirements/requirements.txt
requirements/requirements_loose.txt
requirements/requirements_structuremap.txt
requirements/requirements_structuremap_loose.txt
alphamap-0.2.0.dist-info/LICENSE
alphamap-0.2.0.dist-info/METADATA
alphamap-0.2.0.dist-info/WHEEL
alphamap-0.2.0.dist-info/entry_points.txt
alphamap-0.2.0.dist-info/top_level.txt
alphamap-0.2.0.dist-info/RECORD
