Metadata-Version: 2.2
Name: alphamap
Version: 0.2.0
Author-email: "Isabell Bludau, Eugenia Voytik" <bludau@biochem.mpg.de>
Project-URL: Paper preprint, https://www.biochem.mpg.de/mann
Project-URL: Repository, https://github.com/MannLabs/alphamap
Project-URL: Issues, https://github.com/MannLabs/alphamap/issues
Project-URL: Mann Labs Homepage, https://www.biochem.mpg.de/mann
Keywords: mass spectrometry,proteomics,search engine,DIA,data-independent acquisition,bioinformatics,AlphaPept,AlphaPept ecosystem
Classifier: Development Status :: 4 - Beta
Classifier: Intended Audience :: Science/Research
Classifier: License :: OSI Approved :: Apache Software License
Classifier: Operating System :: OS Independent
Classifier: Programming Language :: Python :: 3
Classifier: Topic :: Scientific/Engineering :: Bio-Informatics
Requires-Python: >=3.8.0
License-File: LICENSE
Requires-Dist: numpy
Requires-Dist: pandas
Requires-Dist: panel
Requires-Dist: param
Requires-Dist: plotly
Requires-Dist: pyteomics
Requires-Dist: pdfrw
Requires-Dist: psutil
Requires-Dist: reportlab
Requires-Dist: kaleido
Requires-Dist: bokeh
Requires-Dist: h5py
Provides-Extra: stable
Requires-Dist: numpy==1.24.4; extra == "stable"
Requires-Dist: pandas==1.4.0; extra == "stable"
Requires-Dist: panel==0.10.3; extra == "stable"
Requires-Dist: param==1.10.0; extra == "stable"
Requires-Dist: plotly==4.12.0; extra == "stable"
Requires-Dist: pyteomics==4.3.3; extra == "stable"
Requires-Dist: pdfrw==0.4; extra == "stable"
Requires-Dist: psutil==5.8.0; extra == "stable"
Requires-Dist: reportlab==3.5.59; extra == "stable"
Requires-Dist: kaleido==0.2.1; extra == "stable"
Requires-Dist: bokeh==2.2.2; extra == "stable"
Requires-Dist: h5py==3.7.0; extra == "stable"
Requires-Dist: jinja2==2.11.3; extra == "stable"
Requires-Dist: markupsafe==2.0.1; extra == "stable"
Provides-Extra: structuremap
Requires-Dist: structuremap; extra == "structuremap"
Provides-Extra: structuremap-stable
Requires-Dist: structuremap==0.0.8; extra == "structuremap-stable"
